LICENSE
MANIFEST.in
README.rst
TODO.rst
setup.py
test_yt-songs.py
yt_songs/__init__.py
yt_songs/yt_songs.py
yt_songs.egg-info/PKG-INFO
yt_songs.egg-info/SOURCES.txt
yt_songs.egg-info/dependency_links.txt
yt_songs.egg-info/entry_points.txt
yt_songs.egg-info/not-zip-safe
yt_songs.egg-info/requires.txt
yt_songs.egg-info/top_level.txt
yt_songs/data/yt-songs.yaml
yt_songs/data/yt-videos.yaml