Metadata-Version: 1.1
Name: yt-songs
Version: 1.0.5
Summary: YT Songs searches, downloads and normalizes the titlesof a list of songs from youtube using youtube-dl.
Home-page: https://github.com/MinikOlsen/yt-songs
Author: Minik Olsen
Author-email: minikolsen9@gmail.com
License: Copyright 2016 Minik Olsen
